data_elegant/__init__.py
data_elegant/cleaner.py
data_elegant/filter.py
data_elegant-0.2.dist-info/METADATA
data_elegant-0.2.dist-info/WHEEL
data_elegant-0.2.dist-info/top_level.txt
data_elegant-0.2.dist-info/RECORD
